MANIFEST.in
README.rst
readme.rst
requirements.txt
setup.py
taskwarrior_context_capsule/__init__.py
taskwarrior_context_capsule/capsule.py
taskwarrior_context_capsule.egg-info/PKG-INFO
taskwarrior_context_capsule.egg-info/SOURCES.txt
taskwarrior_context_capsule.egg-info/dependency_links.txt
taskwarrior_context_capsule.egg-info/entry_points.txt
taskwarrior_context_capsule.egg-info/requires.txt
taskwarrior_context_capsule.egg-info/top_level.txt