Metadata-Version: 1.1
Name: taskwarrior-context-capsule
Version: 0.3.2
Summary: Implementation of Taskwarrior's 'Context' RFC.
Home-page: https://github.com/coddingtonbear/taskwarrior-context-capsule
Author: Adam Coddington
Author-email: me@adamcoddington.net
License: UNKNOWN
Platform: UNKNOWN
Classifier: License :: OSI Approved :: MIT License
Classifier: Operating System :: OS Independent
Classifier: Programming Language :: Python :: 3
